nlmatcher/__init__.py
nlmatcher/location_matcher.py
nlmatcher/patterns.py
nlmatcher/rules/cfg
nlmatcher/rules/patterns.jsonl
nl_matcher-0.0.5.dist-info/METADATA
nl_matcher-0.0.5.dist-info/WHEEL
nl_matcher-0.0.5.dist-info/RECORD
